app_image_generator/__init__.py
app_image_generator/cli.py
app_image_generator/deployment.py
app_image_generator/scripts.py
app_image_generator/startup.py
app_image_generator/plugins/__init__.py
app_image_generator/plugins/base.py
app_image_generator/plugins/slack.py
app_image_generator/plugins/spinnaker.py
app_image_generator-0.2.13.dist-info/METADATA
app_image_generator-0.2.13.dist-info/WHEEL
app_image_generator-0.2.13.dist-info/entry_points.txt
app_image_generator-0.2.13.dist-info/top_level.txt
app_image_generator-0.2.13.dist-info/RECORD
