Metadata-Version: 2.1
Name: app-image-generator
Version: 0.2.13
Summary: UNKNOWN
Home-page: UNKNOWN
Author: Kristian Øllegaard
Author-email: kristian@oellegaard.com
License: UNKNOWN
Platform: UNKNOWN
Requires-Dist: slacker
Requires-Dist: requests
